Workbook

Sheet Cover
B2: FINANCIAL ANALYTICS DASHBOARD
B3: Data Analytics Portfolio - Aobakwe Notwane
B5: This dashboard demonstrates proficiency in financial data analysis, visualization, and business intelligence.
B7: KEY PERFORMANCE INDICATORS
B9: =Dashboard!C3 -> 0 | D9: =Dashboard!C4 -> 0 | F9: =Dashboard!C5 -> 7615000 | H9: =Dashboard!C6 -> 5761000
B10: Total Revenue | D10: Total Expenses | F10: Net Profit | H10: Profit Margin
B15: WORKBOOK CONTENTS
B17: Sheet Name | C17: Description
B18: Dashboard | C18: Executive summary with KPIs and visualizations
B19: Financial Data | C19: Monthly revenue, expenses, and profit data
B20: Analysis | C20: Variance analysis, trends, and insights
B21: Cover | C21: This navigation page
B24: Note: All financial figures are in South African Rand (ZAR). Dashboard updates automatically when data changes.

Sheet Financial Data
B2: MONTHLY FINANCIAL DATA
B4: Month | C4: Revenue (ZAR) | D4: COGS (ZAR) | E4: Operating Expenses (ZAR) | F4: Gross Profit (ZAR) | G4: Net Profit (ZAR)
B5: Jan 2024 | C5: 485000 | D5: 291000 | E5: 85000 | F5: =C5-D5 -> 194000 | G5: =F5-E5 -> 109000
B6: Feb 2024 | C6: 520000 | D6: 312000 | E6: 88000 | F6: =C6-D6 -> 208000 | G6: =F6-E6 -> 120000
B7: Mar 2024 | C7: 495000 | D7: 297000 | E7: 86000 | F7: =C7-D7 -> 198000 | G7: =F7-E7 -> 112000
B8: Apr 2024 | C8: 580000 | D8: 348000 | E8: 92000 | F8: =C8-D8 -> 232000 | G8: =F8-E8 -> 140000
B9: May 2024 | C9: 610000 | D9: 366000 | E9: 95000 | F9: =C9-D9 -> 244000 | G9: =F9-E9 -> 149000
B10: Jun 2024 | C10: 645000 | D10: 387000 | E10: 98000 | F10: =C10-D10 -> 258000 | G10: =F10-E10 -> 160000
B11: Jul 2024 | C11: 625000 | D11: 375000 | E11: 96000 | F11: =C11-D11 -> 250000 | G11: =F11-E11 -> 154000
B12: Aug 2024 | C12: 670000 | D12: 402000 | E12: 102000 | F12: =C12-D12 -> 268000 | G12: =F12-E12 -> 166000
B13: Sep 2024 | C13: 695000 | D13: 417000 | E13: 105000 | F13: =C13-D13 -> 278000 | G13: =F13-E13 -> 173000
B14: Oct 2024 | C14: 720000 | D14: 432000 | E14: 108000 | F14: =C14-D14 -> 288000 | G14: =F14-E14 -> 180000
B15: Nov 2024 | C15: 750000 | D15: 450000 | E15: 112000 | F15: =C15-D15 -> 300000 | G15: =F15-E15 -> 188000
B16: Dec 2024 | C16: 820000 | D16: 492000 | E16: 125000 | F16: =C16-D16 -> 328000 | G16: =F16-E16 -> 203000
B17: TOTAL | C17: =SUM(C5:C16) -> 7615000 | D17: =SUM(D5:D16) -> 4569000 | E17: =SUM(E5:E16) -> 1192000 | F17: =SUM(F5:F16) -> 3046000 | G17: =SUM(G5:G16) -> 1854000
B18: AVERAGE | C18: =AVERAGE(C5:C16) -> 634583.33 | D18: =AVERAGE(D5:D16) -> 380750 | E18: =AVERAGE(E5:E16) -> 99333.333 | F18: =AVERAGE(F5:F16) -> 253833.33 | G18: =AVERAGE(G5:G16) -> 154500

Sheet Dashboard
B2: EXECUTIVE DASHBOARD
B4: KEY METRICS | E4: EXPENSE BREAKDOWN
B5: Total Revenue | C5: =SUM('Financial Data'!C5:C16) -> 7615000 | E5: Cost of Goods Sold | F5: =SUM('Financial Data'!D5:D16) -> 4569000
B6: Total Expenses | C6: =SUM('Financial Data'!D5:D16)+SUM('Financial Data'!E5:E16) -> 5761000 | E6: Operating Expenses | F6: =SUM('Financial Data'!E5:E16) -> 1192000
B7: Net Profit | C7: =SUM('Financial Data'!G5:G16) -> 1854000 | E7: Total Expenses | F7: =F5+F6 -> 5761000
B8: Profit Margin | C8: =C5/(SUM('Financial Data'!C5:C16)/100) -> 100
B9: Gross Profit Margin | C9: =SUM('Financial Data'!F5:F16)/SUM('Financial Data'!C5:C16)*100 -> 40
B10: Avg Monthly Revenue | C10: =AVERAGE('Financial Data'!C5:C16) -> 634583.33
E13: Expense Category | F13: Amount (ZAR)
E14: COGS | F14: =SUM('Financial Data'!D5:D16) -> 4569000
E15: Operating Expenses | F15: =SUM('Financial Data'!E5:E16) -> 1192000

Sheet Analysis
B2: FINANCIAL ANALYSIS & INSIGHTS
B4: MONTHLY PERFORMANCE ANALYSIS
B6: Month | C6: Revenue | D6: MoM Growth | E6: Net Profit | F6: Profit Margin | G6: Performance
B7: ='Financial Data'!B5 -> Jan 2024 | C7: ='Financial Data'!C5 -> 485000 | D7: N/A | E7: ='Financial Data'!G5 -> 109000 | F7: ='Financial Data'!G5/'Financial Data'!C5 -> 0.22474227 | G7: =IF(F7>0.15,"Excellent",IF(F7>0.12,"Good",IF(F7>0.1,"Average","Below Target"))) -> Excellent
B8: ='Financial Data'!B6 -> Feb 2024 | C8: ='Financial Data'!C6 -> 520000 | D8: =('Financial Data'!C6-'Financial Data'!C5)/'Financial Data'!C5 -> 0.072164948 | E8: ='Financial Data'!G6 -> 120000 | F8: ='Financial Data'!G6/'Financial Data'!C6 -> 0.23076923 | G8: =IF(F8>0.15,"Excellent",IF(F8>0.12,"Good",IF(F8>0.1,"Average","Below Target"))) -> Excellent
B9: ='Financial Data'!B7 -> Mar 2024 | C9: ='Financial Data'!C7 -> 495000 | D9: =('Financial Data'!C7-'Financial Data'!C6)/'Financial Data'!C6 -> -0.048076923 | E9: ='Financial Data'!G7 -> 112000 | F9: ='Financial Data'!G7/'Financial Data'!C7 -> 0.22626263 | G9: =IF(F9>0.15,"Excellent",IF(F9>0.12,"Good",IF(F9>0.1,"Average","Below Target"))) -> Excellent
B10: ='Financial Data'!B8 -> Apr 2024 | C10: ='Financial Data'!C8 -> 580000 | D10: =('Financial Data'!C8-'Financial Data'!C7)/'Financial Data'!C7 -> 0.17171717 | E10: ='Financial Data'!G8 -> 140000 | F10: ='Financial Data'!G8/'Financial Data'!C8 -> 0.24137931 | G10: =IF(F10>0.15,"Excellent",IF(F10>0.12,"Good",IF(F10>0.1,"Average","Below Target"))) -> Excellent
B11: ='Financial Data'!B9 -> May 2024 | C11: ='Financial Data'!C9 -> 610000 | D11: =('Financial Data'!C9-'Financial Data'!C8)/'Financial Data'!C8 -> 0.051724138 | E11: ='Financial Data'!G9 -> 149000 | F11: ='Financial Data'!G9/'Financial Data'!C9 -> 0.2442623 | G11: =IF(F11>0.15,"Excellent",IF(F11>0.12,"Good",IF(F11>0.1,"Average","Below Target"))) -> Excellent
B12: ='Financial Data'!B10 -> Jun 2024 | C12: ='Financial Data'!C10 -> 645000 | D12: =('Financial Data'!C10-'Financial Data'!C9)/'Financial Data'!C9 -> 0.057377049 | E12: ='Financial Data'!G10 -> 160000 | F12: ='Financial Data'!G10/'Financial Data'!C10 -> 0.24806202 | G12: =IF(F12>0.15,"Excellent",IF(F12>0.12,"Good",IF(F12>0.1,"Average","Below Target"))) -> Excellent
B13: ='Financial Data'!B11 -> Jul 2024 | C13: ='Financial Data'!C11 -> 625000 | D13: =('Financial Data'!C11-'Financial Data'!C10)/'Financial Data'!C10 -> -0.031007752 | E13: ='Financial Data'!G11 -> 154000 | F13: ='Financial Data'!G11/'Financial Data'!C11 -> 0.2464 | G13: =IF(F13>0.15,"Excellent",IF(F13>0.12,"Good",IF(F13>0.1,"Average","Below Target"))) -> Excellent
B14: ='Financial Data'!B12 -> Aug 2024 | C14: ='Financial Data'!C12 -> 670000 | D14: =('Financial Data'!C12-'Financial Data'!C11)/'Financial Data'!C11 -> 0.072 | E14: ='Financial Data'!G12 -> 166000 | F14: ='Financial Data'!G12/'Financial Data'!C12 -> 0.24776119 | G14: =IF(F14>0.15,"Excellent",IF(F14>0.12,"Good",IF(F14>0.1,"Average","Below Target"))) -> Excellent
B15: ='Financial Data'!B13 -> Sep 2024 | C15: ='Financial Data'!C13 -> 695000 | D15: =('Financial Data'!C13-'Financial Data'!C12)/'Financial Data'!C12 -> 0.037313433 | E15: ='Financial Data'!G13 -> 173000 | F15: ='Financial Data'!G13/'Financial Data'!C13 -> 0.24892086 | G15: =IF(F15>0.15,"Excellent",IF(F15>0.12,"Good",IF(F15>0.1,"Average","Below Target"))) -> Excellent
B16: ='Financial Data'!B14 -> Oct 2024 | C16: ='Financial Data'!C14 -> 720000 | D16: =('Financial Data'!C14-'Financial Data'!C13)/'Financial Data'!C13 -> 0.035971223 | E16: ='Financial Data'!G14 -> 180000 | F16: ='Financial Data'!G14/'Financial Data'!C14 -> 0.25 | G16: =IF(F16>0.15,"Excellent",IF(F16>0.12,"Good",IF(F16>0.1,"Average","Below Target"))) -> Excellent
B17: ='Financial Data'!B15 -> Nov 2024 | C17: ='Financial Data'!C15 -> 750000 | D17: =('Financial Data'!C15-'Financial Data'!C14)/'Financial Data'!C14 -> 0.041666667 | E17: ='Financial Data'!G15 -> 188000 | F17: ='Financial Data'!G15/'Financial Data'!C15 -> 0.25066667 | G17: =IF(F17>0.15,"Excellent",IF(F17>0.12,"Good",IF(F17>0.1,"Average","Below Target"))) -> Excellent
B18: ='Financial Data'!B16 -> Dec 2024 | C18: ='Financial Data'!C16 -> 820000 | D18: =('Financial Data'!C16-'Financial Data'!C15)/'Financial Data'!C15 -> 0.093333333 | E18: ='Financial Data'!G16 -> 203000 | F18: ='Financial Data'!G16/'Financial Data'!C16 -> 0.24756098 | G18: =IF(F18>0.15,"Excellent",IF(F18>0.12,"Good",IF(F18>0.1,"Average","Below Target"))) -> Excellent
B21: KEY INSIGHTS & FINDINGS
B23: Highest Revenue Month | C23: =INDEX('Financial Data'!B5:B16,MATCH(MAX('Financial Data'!C5:C16),'Financial Data'!C5:C16,0)) -> Dec 2024
B24: Highest Revenue Amount | C24: =MAX('Financial Data'!C5:C16) -> 820000
B25: Lowest Revenue Month | C25: =INDEX('Financial Data'!B5:B16,MATCH(MIN('Financial Data'!C5:C16),'Financial Data'!C5:C16,0)) -> Jan 2024
B26: Lowest Revenue Amount | C26: =MIN('Financial Data'!C5:C16) -> 485000
B27: Average Monthly Growth | C27: =AVERAGE(D8:D18) -> 0.050380299
B28: Best Profit Margin | C28: =MAX(F7:F18) -> 0.25066667
B31: SUMMARY STATISTICS
B33: Metric | C33: Value
B34: Total Revenue | C34: =SUM('Financial Data'!C5:C16) -> 7615000
B35: Total Expenses | C35: =SUM('Financial Data'!D5:D16)+SUM('Financial Data'!E5:E16) -> 5761000
B36: Total Net Profit | C36: =SUM('Financial Data'!G5:G16) -> 1854000
B37: Average Monthly Revenue | C37: =AVERAGE('Financial Data'!C5:C16) -> 634583.33
B38: Revenue Std Deviation | C38: =STDEV('Financial Data'!C5:C16) -> 103867.45
B39: Overall Profit Margin | C39: =SUM('Financial Data'!G5:G16)/SUM('Financial Data'!C5:C16) -> 0.24346684
